aestream-0.6.4.dist-info/WHEEL
aestream-0.6.4.dist-info/RECORD
aestream-0.6.4.dist-info/METADATA
aestream-0.6.4.dist-info/licenses/AUTHORS
aestream-0.6.4.dist-info/licenses/LICENSE
aestream.scripts/aestream
bin/flatc
aestream-0.6.4.data/scripts/aestream
include/flatbuffers/minireflect.h
include/flatbuffers/hash.h
include/flatbuffers/buffer_ref.h
include/flatbuffers/util.h
include/flatbuffers/array.h
include/flatbuffers/vector_downward.h
include/flatbuffers/registry.h
include/flatbuffers/grpc.h
include/flatbuffers/buffer.h
include/flatbuffers/reflection.h
include/flatbuffers/code_generators.h
include/flatbuffers/flex_flat_util.h
include/flatbuffers/reflection_generated.h
include/flatbuffers/bfbs_generator.h
include/flatbuffers/stl_emulation.h
include/flatbuffers/default_allocator.h
include/flatbuffers/string.h
include/flatbuffers/code_generator.h
include/flatbuffers/detached_buffer.h
include/flatbuffers/flatc.h
include/flatbuffers/flatbuffer_builder.h
include/flatbuffers/flatbuffers.h
include/flatbuffers/base.h
include/flatbuffers/allocator.h
include/flatbuffers/vector.h
include/flatbuffers/flexbuffers.h
include/flatbuffers/idl.h
include/flatbuffers/table.h
include/flatbuffers/struct.h
include/flatbuffers/verifier.h
include/flatbuffers/pch/flatc_pch.h
include/flatbuffers/pch/pch.h
lib64/libaestream_file.a
lib64/libaestream_input.a
lib64/libaestream_output.a
lib64/libflatbuffers.a
lib64/libaer.a
lib64/cmake/flatbuffers/FlatBuffersTargets.cmake
lib64/cmake/flatbuffers/FlatcTargets-release.cmake
lib64/cmake/flatbuffers/FlatBuffersTargets-release.cmake
lib64/cmake/flatbuffers/FlatcTargets.cmake
lib64/cmake/flatbuffers/BuildFlatBuffers.cmake
lib64/cmake/flatbuffers/flatbuffers-config-version.cmake
lib64/cmake/flatbuffers/flatbuffers-config.cmake
lib64/pkgconfig/flatbuffers.pc
aestream.libs/libSDL2-2-d214786e.0.so.0.10.0
aestream.libs/liblz4-a5753129.so.1.8.3
aestream/__init__.py
aestream/py.typed
aestream/aestream_ext.cpython-39-x86_64-linux-gnu.so
aestream/libaestream_file.a
aestream/libaestream_input.a
aestream/libaestream_output.a
aestream/__init__.pyi
aestream/_input.py
