Metadata-Version: 2.1
Name: aestream
Version: 0.6.4
Summary: Streaming library for Address-Event Representation (AER) data
Author-Email: "Jens E. Pedersen" <jens@jepedersen.dk>
License: MIT
Classifier: License :: OSI Approved :: MIT License
Classifier: Programming Language :: Python :: 3
Classifier: Programming Language :: C++
Classifier: Topic :: Software Development :: Libraries
Classifier: Topic :: System :: Hardware :: Universal Serial Bus (USB)
Project-URL: Homepage, https://github.com/aestream/aestream
Project-URL: Documentation, https://aestream.github.io/aestream
Requires-Python: >=3.8
Requires-Dist: numpy
Requires-Dist: nanobind>=1.2
Requires-Dist: pysdl2
Requires-Dist: pysdl2-dll
